erosion/Scraper.py
erosion/__init__.py
erosion/db_pb2.py
erosion/head.py
erosion/main.py
erosion/midhash.py
erosion/pare_xml.py
erosion-0.0.3.dist-info/METADATA
erosion-0.0.3.dist-info/WHEEL
erosion-0.0.3.dist-info/entry_points.txt
erosion-0.0.3.dist-info/top_level.txt
erosion-0.0.3.dist-info/RECORD
