Metadata-Version: 2.1
Name: erosion
Version: 0.0.3
Summary: UNKNOWN
Home-page: UNKNOWN
License: UNKNOWN
Platform: UNKNOWN
Requires-Dist: Google
Requires-Dist: click
Requires-Dist: protobuf
Requires-Dist: requests
Requires-Dist: lxml
